trexx/__init__.py
trexx/__main__.py
trexx/rexx_lib/__init__.py
trexx/rexx_lib/assertions.rex
trexx/utilities/__init__.py
trexx/utilities/background_colors.py
trexx/utilities/exceptions.py
trexx/utilities/logger.py
trexx/utilities/test_case.py
trexx/utilities/test_file.py
trexx/utilities/test_jcl.py
testrexx-0.4.0.dist-info/LICENSE
testrexx-0.4.0.dist-info/METADATA
testrexx-0.4.0.dist-info/WHEEL
testrexx-0.4.0.dist-info/top_level.txt
testrexx-0.4.0.dist-info/RECORD
